bartender/__init__.py
bartender/__main__.py
bartender/_version.py
bartender/app.py
bartender/errors.py
bartender/mongo_pruner.py
bartender/monitor.py
bartender/pika.py
bartender/pyrabbit.py
bartender/request_validator.py
bartender/specification.py
bartender/local_plugins/__init__.py
bartender/local_plugins/env_help.py
bartender/local_plugins/loader.py
bartender/local_plugins/logger.py
bartender/local_plugins/manager.py
bartender/local_plugins/monitor.py
bartender/local_plugins/plugin_runner.py
bartender/local_plugins/registry.py
bartender/local_plugins/validator.py
bartender/thrift/__init__.py
bartender/thrift/handler.py
bartender/thrift/server.py
bartender-2.4.11.dist-info/LICENSE.md
bartender-2.4.11.dist-info/METADATA
bartender-2.4.11.dist-info/WHEEL
bartender-2.4.11.dist-info/entry_points.txt
bartender-2.4.11.dist-info/top_level.txt
bartender-2.4.11.dist-info/RECORD
