Metadata-Version: 2.1
Name: bartender
Version: 2.4.11
Summary: Beergarden Backend
Home-page: https://beer-garden.io
Author: The beer-garden Team
Author-email: bartender@beer-garden.io
License: MIT
Keywords: bartender beer beer-garden beergarden
Platform: UNKNOWN
Classifier: Development Status :: 4 - Beta
Classifier: Intended Audience :: Developers
Classifier: License :: OSI Approved :: MIT License
Classifier: Natural Language :: English
Classifier: Programming Language :: Python :: 2
Classifier: Programming Language :: Python :: 2.7
Classifier: Programming Language :: Python :: 3
Classifier: Programming Language :: Python :: 3.5
Classifier: Programming Language :: Python :: 3.6
Classifier: Programming Language :: Python :: 3.7
Classifier: Programming Language :: Python :: 3.8
Requires-Dist: bg-utils (>=2.4.4)
Requires-Dist: pyrabbit2 (==1.0.7)
Requires-Dist: pymongo (<4)
Requires-Dist: future (>=0.16.0) ; python_version=="2.7"
Requires-Dist: futures (>=3.1.1) ; python_version=="2.7"
Requires-Dist: subprocess32 (>=3.2.7) ; python_version=="2.7"
